odoo/addons/crowdfunding_claim/README.rst
odoo/addons/crowdfunding_claim/__init__.py
odoo/addons/crowdfunding_claim/__manifest__.py
odoo/addons/crowdfunding_claim/controllers/__init__.py
odoo/addons/crowdfunding_claim/controllers/main.py
odoo/addons/crowdfunding_claim/i18n/crowdfunding_claim.pot
odoo/addons/crowdfunding_claim/i18n/it.po
odoo/addons/crowdfunding_claim/models/__init__.py
odoo/addons/crowdfunding_claim/models/crowdfunding_challenge.py
odoo/addons/crowdfunding_claim/readme/CONTRIBUTORS.md
odoo/addons/crowdfunding_claim/readme/DESCRIPTION.md
odoo/addons/crowdfunding_claim/readme/USAGE.md
odoo/addons/crowdfunding_claim/static/description/icon.png
odoo/addons/crowdfunding_claim/static/description/index.html
odoo/addons/crowdfunding_claim/templates/crowdfunding_challenge.xml
odoo14_addon_crowdfunding_claim-14.0.1.1.0.dist-info/METADATA
odoo14_addon_crowdfunding_claim-14.0.1.1.0.dist-info/WHEEL
odoo14_addon_crowdfunding_claim-14.0.1.1.0.dist-info/top_level.txt
odoo14_addon_crowdfunding_claim-14.0.1.1.0.dist-info/RECORD
